pydupfinder/__init__.py
pydupfinder/pydupfinder.py
pydupfinder-2.0.1.dist-info/LICENSE.md
pydupfinder-2.0.1.dist-info/METADATA
pydupfinder-2.0.1.dist-info/entry_points.txt
pydupfinder-2.0.1.dist-info/WHEEL
pydupfinder-2.0.1.dist-info/RECORD
