Metadata-Version: 2.1
Name: pydupfinder
Version: 2.0.1
Summary: 
Author: Alexey Vyskubov
Author-email: alexey@ocaml.nl
Requires-Python: >=3.10,<4.0
Classifier: Programming Language :: Python :: 3
Classifier: Programming Language :: Python :: 3.10
Classifier: Programming Language :: Python :: 3.11
Requires-Dist: click (>=8.1.3,<9.0.0)
Requires-Dist: click-option-group (>=0.5.5,<0.6.0)
